pyhacl/__init__.py
pyhacl/__main__.py
pyhacl/drbg.cpython-311-x86_64-linux-gnu.so
pyhacl/drbg.py
pyhacl/hmac.cpython-311-x86_64-linux-gnu.so
pyhacl/hmac.py
pyhacl/aead/__init__.py
pyhacl/aead/chacha_poly1305.cpython-311-x86_64-linux-gnu.so
pyhacl/aead/chacha_poly1305.py
pyhacl/diffie_hellman/__init__.py
pyhacl/diffie_hellman/curve25519.cpython-311-x86_64-linux-gnu.so
pyhacl/diffie_hellman/curve25519.py
pyhacl/hashlib/__init__.py
pyhacl/hashlib/sha2.cpython-311-x86_64-linux-gnu.so
pyhacl/hashlib/sha2.py
pyhacl/signature/__init__.py
pyhacl/signature/ed25519.cpython-311-x86_64-linux-gnu.so
pyhacl/signature/ed25519.py
pyhacl/signature/p256.cpython-311-x86_64-linux-gnu.so
pyhacl/signature/p256.py
pyhacl-1.0.1.dist-info/METADATA
pyhacl-1.0.1.dist-info/WHEEL
pyhacl-1.0.1.dist-info/top_level.txt
pyhacl-1.0.1.dist-info/RECORD
pyhacl-1.0.1.dist-info/licenses/LICENSE
