Metadata-Version: 2.4
Name: pyhacl
Version: 1.0.1
Summary: Python binding to the HACL* library
Author: Julien Castiaux
Author-email: julien.castiaux@mailfence.com
License: Apache-2.0
Project-URL: Download, https://pypi.org/project/pyhacl/
Project-URL: Repository, https://codeberg.org/drlazor8/pyhacl
Project-URL: Documentation, https://pyhacl.readthedocs.io/en/latest/
Classifier: Development Status :: 4 - Beta
Classifier: Intended Audience :: Developers
Classifier: Operating System :: OS Independent
Classifier: Programming Language :: Cython
Classifier: Programming Language :: Python :: 3
Classifier: Programming Language :: Python :: 3.10
Classifier: Programming Language :: Python :: 3.11
Classifier: Programming Language :: Python :: 3.12
Classifier: Programming Language :: Python :: 3.13
Classifier: Topic :: Security :: Cryptography
Requires-Python: >=3.10
License-File: LICENSE
Requires-Dist: cython>=3.1
Provides-Extra: dev
Requires-Dist: build; extra == "dev"
Requires-Dist: parameterized; extra == "dev"
Requires-Dist: sphinx; extra == "dev"
Requires-Dist: furo; extra == "dev"
Dynamic: author
Dynamic: author-email
Dynamic: classifier
Dynamic: description
Dynamic: license
Dynamic: license-file
Dynamic: project-url
Dynamic: provides-extra
Dynamic: requires-dist
Dynamic: requires-python
Dynamic: summary
